molo.usermetadata-6.0.0-py2.7-nspkg.pth
molo/usermetadata/__init__.py
molo/usermetadata/middleware.py
molo/usermetadata/models.py
molo/usermetadata/urls.py
molo/usermetadata/views.py
molo/usermetadata/migrations/0001_initial.py
molo/usermetadata/migrations/0002_create_index_page.py
molo/usermetadata/migrations/0003_persona_settings.py
molo/usermetadata/migrations/__init__.py
molo/usermetadata/templates/persona.html
molo/usermetadata/templatetags/__init__.py
molo/usermetadata/templatetags/persona_tags.py
molo/usermetadata/test_templates/base.html
molo/usermetadata/tests/__init__.py
molo/usermetadata/tests/test_tags.py
molo/usermetadata/tests/test_views.py
molo.usermetadata-6.0.0.dist-info/METADATA
molo.usermetadata-6.0.0.dist-info/RECORD
molo.usermetadata-6.0.0.dist-info/WHEEL
molo.usermetadata-6.0.0.dist-info/namespace_packages.txt
molo.usermetadata-6.0.0.dist-info/top_level.txt
