Metadata-Version: 2.1
Name: molo.usermetadata
Version: 6.0.0
Summary: User metadata to be used with Molo.
Home-page: http://github.com/praekelt/molo.usermetadata
Author: Praekelt.org
Author-email: dev@praekelt.org
License: BSD
Keywords: praekelt,mobi,web,django
Platform: UNKNOWN
Classifier: Programming Language :: Python
Classifier: Framework :: Django
Classifier: Topic :: Internet :: WWW/HTTP
Classifier: Topic :: Internet :: WWW/HTTP :: WSGI :: Application
Provides-Extra: test
Provides-Extra: lint
Provides-Extra: cover
Requires-Dist: molo.core (<=7.0.0,>=6.0.0)
Provides-Extra: cover
Requires-Dist: pytest-cov; extra == 'cover'
Provides-Extra: lint
Requires-Dist: flake8 (==3.4.1); extra == 'lint'
Provides-Extra: test
Requires-Dist: pytest (==3.0.0); extra == 'test'
Requires-Dist: pytest-django (==3.1.1); extra == 'test'
Requires-Dist: responses; extra == 'test'
